{"phLRDWGi3MXg7rDZmx1nMg==":"img-9911.jpg","bkQ/Zv9EYe1AJbHLxUv7TA==":"img-8832.jpg","P/mkyn6LHHY28tnfi+cQdQ==":"62339905105-42ec3e82-2a34-40a4-a5f5-57a95b3809a1.jpeg","cjs4TUEHP/ZPxkvVnSl24w==":"img-9303.jpeg","vUgX64RtlunqKO84ulRS0g==":"img-4515.jpeg","6p9lJYdDR3YNZUn32hYBhA==":"img-911.jpg","d/es5bfsZYg7tolfAII9+Q==":"img-818.jpeg","qSaaP9rXZ37MTvNrKoalpQ==":"img-9362.jpeg","nn2NrsIDYssC3SDjdqS8JQ==":"img-8432.png","0bUbylm1Kbm19Z9j+hvJ1w==":"img-4367.jpg","wTLZLQhycP59kBEAwy3UeQ==":"62339905105-42ec3e82-2a34-40a4-a5f5-57a95b3809a1-1.jpeg","CrNWRx3FMW/LCIwnprcmuA==":"img-8431.jpg"}